LICENSE
README.md
setup.py
Estrapy/__init__.py
Estrapy/autoupdate.py
Estrapy/base.py
Estrapy/cli.py
Estrapy/errors.py
Estrapy/games.py
Estrapy/help.py
Estrapy/http.py
Estrapy/nsfw.py
Estrapy/osu.py
Estrapy/property.py
Estrapy/sfw.py
Estrapy/trivia.py
Estrapy_API.egg-info/PKG-INFO
Estrapy_API.egg-info/SOURCES.txt
Estrapy_API.egg-info/dependency_links.txt
Estrapy_API.egg-info/entry_points.txt
Estrapy_API.egg-info/requires.txt
Estrapy_API.egg-info/top_level.txt