Metadata-Version: 2.1
Name: Estrapy-API
Version: 0.2.7
Summary: An Easy-to-Use Wrapper Anime Images API with Many Others Features
Home-page: https://github.com/StawaDev/Estrapy-API
Author: StawaDev
License: MIT
Project-URL: Documentation, https://stawa.gitbook.io/estraapi-documentation/
Project-URL: Source, https://github.com/StawaDev/Estrapy-API
Project-URL: Tracker, https://github.com/StawaDev/Estrapy-API/issues
Keywords: python api,anime,anime gif,roleplay gif,wrapper anime gif,osu,osu api,trivia
Classifier: Development Status :: 3 - Alpha
Classifier: Programming Language :: Python :: 3
Classifier: License :: OSI Approved :: MIT License
Classifier: Natural Language :: English
Classifier: Environment :: Console
Provides-Extra: cli
License-File: LICENSE
